duct.py
duct-1.0.1.dist-info/METADATA
duct-1.0.1.dist-info/WHEEL
duct-1.0.1.dist-info/licenses/LICENSE
duct-1.0.1.dist-info/RECORD
