Metadata-Version: 2.4
Name: duct
Version: 1.0.1
Summary: a library for running child processes
Project-URL: Repository, https://github.com/oconnor663/duct.py
Project-URL: Documentation, https://ductpy.readthedocs.io
Author-email: Jack O'Connor <oconnor663@gmail.com>
License-Expression: MIT
License-File: LICENSE
Requires-Python: >=3.9
